ElasticEmail/__init__.py
ElasticEmail/api_client.py
ElasticEmail/api_response.py
ElasticEmail/configuration.py
ElasticEmail/exceptions.py
ElasticEmail/py.typed
ElasticEmail/rest.py
ElasticEmail/api/__init__.py
ElasticEmail/api/campaigns_api.py
ElasticEmail/api/contacts_api.py
ElasticEmail/api/domains_api.py
ElasticEmail/api/emails_api.py
ElasticEmail/api/events_api.py
ElasticEmail/api/files_api.py
ElasticEmail/api/inbound_route_api.py
ElasticEmail/api/lists_api.py
ElasticEmail/api/security_api.py
ElasticEmail/api/segments_api.py
ElasticEmail/api/statistics_api.py
ElasticEmail/api/sub_accounts_api.py
ElasticEmail/api/suppressions_api.py
ElasticEmail/api/templates_api.py
ElasticEmail/api/verifications_api.py
ElasticEmail/models/__init__.py
ElasticEmail/models/access_level.py
ElasticEmail/models/account_status_enum.py
ElasticEmail/models/api_key.py
ElasticEmail/models/api_key_payload.py
ElasticEmail/models/body_content_type.py
ElasticEmail/models/body_part.py
ElasticEmail/models/campaign.py
ElasticEmail/models/campaign_options.py
ElasticEmail/models/campaign_recipient.py
ElasticEmail/models/campaign_status.py
ElasticEmail/models/campaign_template.py
ElasticEmail/models/certificate_validation_status.py
ElasticEmail/models/channel_log_status_summary.py
ElasticEmail/models/compression_format.py
ElasticEmail/models/consent_data.py
ElasticEmail/models/consent_tracking.py
ElasticEmail/models/contact.py
ElasticEmail/models/contact_activity.py
ElasticEmail/models/contact_payload.py
ElasticEmail/models/contact_source.py
ElasticEmail/models/contact_status.py
ElasticEmail/models/contact_update_payload.py
ElasticEmail/models/contacts_list.py
ElasticEmail/models/delivery_optimization_type.py
ElasticEmail/models/domain_data.py
ElasticEmail/models/domain_detail.py
ElasticEmail/models/domain_owner.py
ElasticEmail/models/domain_payload.py
ElasticEmail/models/domain_update_payload.py
ElasticEmail/models/email_content.py
ElasticEmail/models/email_data.py
elasticemail-4.1.4.dist-info/METADATA
elasticemail-4.1.4.dist-info/WHEEL
elasticemail-4.1.4.dist-info/top_level.txt
elasticemail-4.1.4.dist-info/RECORD
