Metadata-Version: 2.1
Name: ElasticEmail
Version: 4.1.4
Summary: Elastic Email REST API
Home-page: 
Author: Elastic Email
Author-email: support@elasticemail.com
License: MIT
Keywords: OpenAPI,OpenAPI-Generator,Elastic Email REST API
Requires-Python: >=3.6
Requires-Dist: urllib3 >=1.25.3
Requires-Dist: python-dateutil
